yasgi/__init__.py
yasgi/asgi.py
yasgi/exceptions.py
yasgi/requests.py
yasgi/responses.py
yasgi/routing.py
yasgi-0.1.0.dist-info/LICENSE
yasgi-0.1.0.dist-info/WHEEL
yasgi-0.1.0.dist-info/METADATA
yasgi-0.1.0.dist-info/RECORD
