Metadata-Version: 2.1
Name: yasgi
Version: 0.1.0
Summary: Yasgi is a Tiny Web Framework for Python, aiming to be as simple as possible.
Home-page: https://github.com/yezz123/yasgi
Author: Yasser Tahiri
Author-email: hello@yezz.me
Requires-Python: >=3.9
Classifier: License :: OSI Approved :: GNU General Public License v3 (GPLv3)
Classifier: Operating System :: OS Independent
Classifier: Intended Audience :: Developers
Classifier: Framework :: AsyncIO
Classifier: Programming Language :: Python
Classifier: Programming Language :: Python :: 3.9
Classifier: Programming Language :: Python :: 3.10
Classifier: Programming Language :: Python :: 3 :: Only
Classifier: Topic :: Internet :: WWW/HTTP :: Session
Classifier: Typing :: Typed
Requires-Dist: orjson
Requires-Dist: python-daemon ; extra == "dev"
Requires-Dist: python-dotenv ; extra == "dev"
Requires-Dist: uvicorn[standard] ; extra == "dev"
Requires-Dist: requests ; extra == "dev"
Requires-Dist: pre-commit==2.19.0 ; extra == "lint"
Requires-Dist: mypy==0.931 ; extra == "lint"
Requires-Dist: pytest==7.1.2 ; extra == "test"
Requires-Dist: pytest-asyncio == 0.18.3 ; extra == "test"
Requires-Dist: codecov==2.1.12 ; extra == "test"
Requires-Dist: pytest-cov==3.0.0 ; extra == "test"
Project-URL: Source, https://github.com/yezz123/yasgi
Provides-Extra: dev
Provides-Extra: lint
Provides-Extra: test
